rt_opt/__init__.py
rt_opt/global_search.py
rt_opt/local_search.py
rt_opt/optimizer.py
rt_opt/testproblems.py
rt_opt/testproblems_shifted.py
rt_opt-0.2.0.dist-info/LICENSE
rt_opt-0.2.0.dist-info/METADATA
rt_opt-0.2.0.dist-info/WHEEL
rt_opt-0.2.0.dist-info/top_level.txt
rt_opt-0.2.0.dist-info/RECORD
