Metadata-Version: 2.1
Name: rt_opt
Version: 0.2.0
Summary: Metaheuristic global optimization algorithm
Home-page: https://github.com/don-alejandrino/rt_opt
Author: Alexander Geiseler
Author-email: don-alejandrino@outlook.com
Project-URL: Bug Tracker, https://github.com/don-alejandrino/rt_opt/issues
Classifier: Programming Language :: Python :: 3
Classifier: License :: OSI Approved :: MIT License
Classifier: Operating System :: OS Independent
Requires-Python: >=3.10
License-File: LICENSE
Requires-Dist: numpy ~=1.26.4
Requires-Dist: scipy ~=1.12.0
